{"node-129-lobby": "place-forhl", "door-knncl-sbmain": "place-knncl", "node-armnl-wescstairs-lobby": "place-armnl", "node-935-platform": "place-wtcst", "70238": "place-clmnl", "70007": "place-jaksn", "node-haecl-congogplatn-passage": "place-haecl", "door-prmnl-prudential": "place-prmnl", "node-147-platform": "place-tumnl", "node-427-platform": "place-fldcr", "door-crtst-south": "place-crtst", "node-symcl-wb-farepaid": "place-symcl", "node-sull-sbstairs-platform": "place-sull", "node-lbusramp-lower": "place-sull", "door-cntsq-western": "place-cntsq", "node-966-lobby": "place-mvbcl", "node-710-platform": "place-wondl", "node-962-platform": "place-armnl", "70197": "place-pktrm", "node-nqncy-senterramp-bus": "place-nqncy", "node-325-platform": "place-nqncy", "node-shmnl-sh-fareunpaid": "place-shmnl", "node-spmnl-obstairs-lobby": "place-spmnl", "node-knncl-nbmain-farepaid": "place-knncl", "70240": "place-prmnl", "node-940-entrance": "place-crtst", "node-428-lobby": "place-mvbcl", "74624": "place-conrd", "door-state-exchange": "place-state", "door-cntsq-prospect": "place-cntsq", "node-tumnl-trenbstairs-lobby": "place-tumnl", "node-fldcr-ashstair-platform": "place-fldcr", "door-north-valenti": "place-north", "node-856-platform": "place-bbsta", "node-917-lobby": "place-prmnl", "node-jfk-crcolstair-columbia": "place-jfk", "Walpole-S": "place-FB-0191", "node-aport-wbpaidstairs-bridge": "place-aport", "node-smmnl-farepaid": "place-smmnl", "node-948-lobby": "place-kencl", "node-dwnxg-stair13-lobby": "place-dwnxg", "node-pktrm-ebparkstairs-lobby": "place-pktrm", "node-897-street": "place-nqncy", "door-forhl-lower": "place-forhl", "node-869-lobby": "place-dwnxg", "node-127-busway": "place-forhl", "node-sstat-918stair-lobby": "place-sstat", "node-pktrm-tremefare-paid": "place-pktrm", "South Acton": "place-FR-0253", "door-asmnl-rdexits": "place-asmnl", "node-jfk-braganstair-lobby": "place-jfk", "node-896-platform": "place-qnctr", "70087": "place-shmnl", "70059": "place-wondl", "node-939-entrance": "place-crtst", "door-newtn-hyde": "place-newtn", "node-434-entrance": "place-mvbcl", "node-mlmnl-exitstair-platform": "place-mlmnl", "node-144-platform": "place-bbsta", "door-chncl-ogessex": "place-chncl", "node-sstat-400stair-middle": "place-sstat", "node-wondl-nshoreplazastairs-plaza": "place-wondl", "door-bbsta-dartmn": "place-bbsta", "node-bbsta-lower-farepaid": "place-bbsta", "node-416-platform": "place-crtst", "node-prmnl-wbstair-lobby": "place-prmnl", "door-rugg-columbus": "place-rugg", "node-pktrm-nbexitpaid": "place-pktrm", "70160": "place-river", "node-436-platform": "place-armnl", "70265": "place-butlr", "node-sstat-411stair-lobby": "place-sstat", "70154": "place-coecl", "door-dwnxg-temple": "place-dwnxg", "South Station-05": "place-sstat", "node-112-platform": "place-dwnxg", "node-dwnxg-concourse": "place-dwnxg", "70111": "place-sougr", "node-masta-unpaid-lobby": "place-masta", "70258": "place-bckhl", "node-kencl-beacstair-lobby": "place-kencl", "node-cntsq-prospectstair-platform": "place-cntsq", "node-forhl-slowbusstairs-lobby": "place-forhl", "node-harsq-sbstair-nb": "place-harsq", "node-sstat-390stair-rl": "place-sstat", "node-810-platform": "place-qnctr", "node-947-lobby": "place-shmnl", "node-grnst-844-lobby": "place-grnst", "node-308-lobby": "place-sull", "door-qnctr-burgin": "place-qnctr", "70271": "place-valrd", "node-masta-fareunpaid": "place-masta", "70091": "place-smmnl", "door-butlr-branchfield": "place-butlr", "node-orhte-sara-farepaid": "place-orhte", "node-qnctr-rdstair-entrance": "place-qnctr", "node-151-street": "place-prmnl", "node-brdwy-fareunpaid": "place-brdwy", "node-harsq-sbramp-platform": "place-harsq", "node-knncl-frontnbstair-entrance": "place-knncl", "node-140-lobby": "place-bbsta", "node-913-lobby": "place-aqucl", "node-aqucl-wbstatestairs-platform": "place-aqucl", "node-mlmnl-olstairs-lobby": "place-mlmnl", "door-chhil-museum": "place-chhil", "node-sstat-420stair-middle": "place-sstat", "node-mvbcl-lewfarepaid": "place-mvbcl", "node-welln-skystairs-bridge": "place-welln", "5104": "place-davis", "node-brdwy-farepaid": "place-brdwy", "node-asmnl-radfarepaid": "place-asmnl", "node-931-platform": "place-aport", "node-857-lobby": "place-tumnl", "node-rugg-olnstairs-lobby": "place-rugg", "70252": "place-fenwd", "Sharon": "place-NEC-2108", "node-cntsq-pearlstair-platform": "place-cntsq", "node-jaksn-farepaid": "place-jaksn", "door-astao-revol": "place-astao", "64": "place-dudly", "node-brdwy-platstairs-platform": "place-brdwy", "node-aport-wbpaidstairs-platform": "place-aport", "node-sstat-alewife-farepaid": "place-sstat", "node-811-platform": "place-brntn", "Melrose Highlands": "place-WR-0075", "West Medford": "place-NHRML-0055", "node-fldcr-ashstair-lobby": "place-fldcr", "node-sstat-420sl-middle": "place-sstat", "70204": "place-haecl", "node-armnl-wescstairs-escalator": "place-armnl", "node-138-bottom": "place-rugg", "node-wondl-fareunpaid": "place-wondl", "node-dwnxg-stair7-ol": "place-dwnxg", "70104": "place-qamnl", "node-masta-undersouth-lobby": "place-masta", "70202": "place-gover", "node-906-passage": "place-haecl", "node-knncl-frontsbstair-platform": "place-knncl", "node-958-platform": "place-fldcr", "node-ccmnl-305-platform": "place-ccmnl", "node-879-lobby": "place-andrw", "70067": "place-harsq", "node-dwnxg-stair5-platform": "place-dwnxg", "door-chncl-fhelevator": "place-chncl", "Newburyport": "place-ER-0362", "node-cntsq-861-platform": "place-cntsq", "node-427-lobby": "place-fldcr", "node-931-bridge": "place-aport", "node-702-lobby": "place-wondl", "node-wimnl-ibunpaidstairs-street": "place-wimnl", "node-sstat-bldgescdown-lobby": "place-sstat", "node-394-platform": "place-aqucl", "Back Bay-03": "place-bbsta", "door-brkhl-cypress": "place-brkhl", "node-pktrm-tremwfare-paid": "place-pktrm", "node-orhte-obpaidstairs-platform": "place-orhte", "Hersey": "place-NB-0109", "node-knncl-backsbstair-platform": "place-knncl", "node-symcl-eb-farepaid": "place-symcl", "70199": "place-pktrm", "door-prmnl-huntington": "place-prmnl", "node-bbsta-olestairs-lobby": "place-bbsta", "70060": "place-wondl", "node-masta-undernorth-way": "place-masta", "Blue Hill Avenue": "place-DB-2222", "node-514-lobby": "place-harsq", "South Station-12": "place-sstat", "node-923-lobby": "place-aqucl", "node-398-sl": "place-sstat", "Framingham-S": "place-WML-0214", "node-337-middle": "place-davis", "door-alfcl-steel": "place-alfcl", "door-sdmnl-walley": "place-sdmnl", "node-crtst-southlobstair-lobby": "place-crtst", "70032": "place-welln", "70030": "place-sull", "node-tumnl-washnbstairs-platform": "place-tumnl", "node-123-platform": "place-andrw", "70024": "place-haecl", "node-wondl-nshorestairs-bottom": "place-wondl", "door-wondl-nshore": "place-wondl", "node-brntn-fareunpaid": "place-brntn", "70063": "place-davis", "node-wtcst-ibstairs-lobby": "place-wtcst", "10642": "place-forhl", "North Station-06": "place-north", "70128": "place-grigg", "node-forhl-busfarepaid": "place-forhl", "node-welln-skyentry": "place-welln", "node-dwnxg-wintexitfare-paid": "place-dwnxg", "node-403-lobby": "place-wtcst", "door-state-cityhall": "place-state", "door-jfk-columbia": "place-jfk", "node-symcl-falmstair-platform": "place-symcl", "door-sull-main": "place-sull", "21917": "place-rsmnl", "node-mlmnl-crstairs-platform": "place-mlmnl", "node-bbsta-upasswstairs-bottom": "place-bbsta", "node-wondl-ibplazastairs-bridge": "place-wondl", "node-bomnl-pstair-platform": "place-bomnl", "Alewife-01": "place-alfcl", "node-889-unpaidstreet": "place-wimnl", "node-aport-ebpaidstairs-bridge": "place-aport", "29009": "place-sull", "node-qnctr-center-lobby": "place-qnctr", "door-nqncy-squantum": "place-nqncy", "door-cedgr-hillsdale": "place-cedgr", "node-851-top": "place-rugg", "West Concord": "place-FR-0219", "32002": "place-qnctr", "node-951-platform": "place-chmnl", "70146": "place-buest", "node-396-lobby": "place-aqucl", "node-962-lobby": "place-armnl", "node-dwnxg-stair9-lobby": "place-dwnxg", "node-859-platform": "place-tumnl", "node-wlsta-stair4-platform": "place-wlsta", "node-908-lobby": "place-haecl", "node-kencl-busstair-landing": "place-kencl", "node-masta-unpstair-exit": "place-masta", "Cohasset": "place-GRB-0199", "node-338-lobby": "place-davis", "node-856-lobby": "place-bbsta", "node-masta-mainstair-platform": "place-masta", "node-chmnl-fareunpaid": "place-chmnl", "Swampscott": "place-ER-0128", "node-jfk-ashgasstair-lobby": "place-jfk", "node-rcmnl-fareunpaid": "place-rcmnl", "door-andrw-elevator": "place-andrw", "70029": "place-ccmnl", "node-917-street": "place-prmnl", "door-alfcl-alewife": "place-alfcl", "Whitman": "place-PB-0212", "Windsor Gardens-S": "place-FB-0166", "Franklin-S": "place-FB-0275", "Prides Crossing": "place-GB-0222", "node-mvbcl-msqfarepaid": "place-mvbcl", "node-129-platform": "place-forhl", "70115": "place-chswk", "node-418-entrance": "place-crtst", "node-332-rl": "place-dwnxg", "node-866-entrance": "place-knncl", "node-449-platform": "place-wlsta", "node-harsq-upperramp-upper": "place-harsq", "70260": "place-hsmnl", "node-334-lobby": "place-brntn", "node-brntn-crramp-top": "place-brntn", "node-920-platform": "place-prmnl", "node-gover-fareunpaid": "place-gover", "Oak Grove-01": "place-ogmnl", "node-astao-revplatstair-lobby": "place-astao", "node-970-platform": "place-asmnl", "node-jaksn-stairs-lobby": "place-jaksn", "70155": "place-coecl", "node-pktrm-tremefare-unpaid": "place-pktrm", "Greenwood": "place-WR-0085", "node-masta-undersouth-way": "place-masta", "Back Bay-07": "place-bbsta", "70027": "place-north", "node-dwnxg-stair12-middle": "place-dwnxg", "node-smmnl-954-lobby": "place-smmnl", "Readville": "place-DB-0095", "door-davis-busway": "place-davis", "node-knncl-backnbstair-platform": "place-knncl", "node-870-lobby": "place-dwnxg", "door-coecl-church": "place-coecl", "door-cntsq-pearl": "place-cntsq", "node-orhte-obunpaidstairs-bridge": "place-orhte", "node-433-lobby": "place-mvbcl", "node-335-platform": "place-brntn", "node-astao-716-lobby": "place-astao", "node-142-lobby": "place-bbsta", "70267": "place-miltt", "node-davis-colstairup-entrance": "place-davis", "node-125-lobby": "place-bomnl", "node-pktrm-stair5-gl": "place-pktrm", "Waverley": "place-FR-0074", "70177": "place-bcnfd", "node-390-sl": "place-sstat", "node-wondl-ibplazastairs-lobby": "place-wondl", "node-pktrm-midupassstairs-platform": "place-pktrm", "70228": "place-fbkst", "node-pktrm-sbwinterstairs-platform": "place-pktrm", "74617": "place-sstat", "door-bvmnl-boylston": "place-bvmnl", "South Station-02": "place-sstat", "node-chmnl-farepaid": "place-chmnl", "door-symcl-huntw": "place-symcl", "door-ogmnl-wash": "place-ogmnl", "node-890-paidplatform": "place-wimnl", "node-andrw-nibstairs-lobby": "place-andrw", "node-sstat-419stair-lobby": "place-sstat", "70274": "place-capst", "node-437-lobby": "place-asmnl", "node-rcmnl-stairs-platform": "place-rcmnl", "node-prmnl-wbstair-platform": "place-prmnl", "node-aport-bremen-fareunpaid": "place-aport", "node-433-entrance": "place-mvbcl", "node-prmnl-921ramp-platform": "place-prmnl", "node-420-middle": "place-sstat", "door-dwnxg-hawley": "place-dwnxg", "node-pktrm-nbwinterstairs-platform": "place-pktrm", "node-715-bridge": "place-orhte", "node-wimnl-ibpaidstairs-bridge": "place-wimnl", "node-sstat-outmainstair-lobby": "place-sstat", "node-701-lobby": "place-wondl", "74612": "place-crtst", "South Station-07": "place-sstat", "door-qamnl-pickup": "place-qamnl", "door-welln-busway": "place-welln", "node-wimnl-obunpaidstairs-street": "place-wimnl", "node-412-landing": "place-crtst", "node-chmnl-sbstairs-lobby": "place-chmnl", "door-north-crnashua": "place-north", "70158": "place-boyls", "node-rugg-forsythstairs-top": "place-rugg", "node-367-lobby": "place-brdwy", "node-bbsta-w57stairs-lobby": "place-bbsta", "Lawrence": "place-WR-0264", "node-knncl-nbsec-farepaid": "place-knncl", "node-spmnl-ofarepaid": "place-spmnl", "node-aport-bremenstairs-lobby": "place-aport", "node-gover-nentrancestairs-platform": "place-gover", "node-bbsta-dartexit-farepaid": "place-bbsta", "door-bbsta-buswayn": "place-bbsta", "node-smmnl-nbstairs-platform": "place-smmnl", "70009": "place-rcmnl", "5879": "place-orhte", "node-336-entrance": "place-davis", "node-424-lobby": "place-sstat", "node-jfk-ashcolstair-platform": "place-jfk", "node-fldcr-charlesstairs-lobby": "place-fldcr", "Oak Grove-02": "place-ogmnl", "node-smmnl-nbstairs-lobby": "place-smmnl", "29008": "place-sull", "70096": "place-jfk", "node-grnst-131-platform": "place-grnst", "Ruggles-02": "place-rugg", "Silver Hill": "place-FR-0147", "node-380-bridge": "place-wimnl", "node-922-lobby": "place-chncl", "node-432-lobby": "place-kencl", "door-boyls-outbound": "place-boyls", "door-spmnl-obrienel": "place-spmnl", "node-masta-unpramp-exit": "place-masta", "node-grnst-stairs-platform": "place-grnst", "node-davis-holland-entrance": "place-davis", "Newmarket": "place-DB-2265", "node-423-lobby": "place-shmnl", "74636": "place-estav", "node-dwnxg-sumchyfare-paid": "place-dwnxg", "node-welln-fhstair-platform": "place-welln", "door-sstat-outmain": "place-sstat", "node-jfk-brasydstair-platform": "place-jfk", "2076": "place-harsq", "node-harsq-harfareunpaid": "place-harsq", "node-smmnl-sbstairs-lobby": "place-smmnl", "Fitchburg": "place-FR-0494", "node-andrw-nobstairs-platform": "place-andrw", "node-gover-wbtransstairs-gl": "place-gover", "node-rugg-crstairs-lobby": "place-rugg", "node-jaksn-846-platform": "place-jaksn", "node-366-landing": "place-chncl", "node-968-platform": "place-asmnl", "Wellesley Farms": "place-WML-0125", "node-astao-442-lobby": "place-astao", "node-wlsta-stair1-bridge": "place-wlsta", "node-135-busway": "place-rugg", "node-879-platform": "place-andrw", "door-wlsta-newpsouth": "place-wlsta", "node-symcl-wb-ebottom": "place-symcl", "node-symcl-wb-wtop": "place-symcl", "door-aqucl-mcknorth": "place-aqucl", "Gloucester": "place-GB-0316", "node-lech-farepaid": "place-lech", "185": "place-matt", "door-forhl-arborway": "place-forhl", "door-jfk-oldcolony": "place-jfk", "70076": "place-pktrm", "node-rugg-olsstairs-platform": "place-rugg", "node-qnctr-fareunpaid": "place-qnctr", "node-892-lobby": "place-dwnxg", "node-362-platform": "place-knncl", "node-386-lobby": "place-sstat", "node-crtst-southentstair-entrance": "place-crtst", "node-903-platform": "place-haecl", "70213": "place-hwsst", "node-898-lobby": "place-nqncy", "door-bbsta-clarcolum": "place-bbsta", "node-377-lobby": "place-chncl", "node-fldcr-farepaid": "place-fldcr", "node-coecl-439-platform": "place-coecl", "node-sstat-918stair-sl": "place-sstat", "node-ogmnl-banksstair-street": "place-ogmnl", "node-903-lobby": "place-haecl", "Ruggles": "place-rugg", "node-714-bridge": "place-orhte", "node-pktrm-stair4-platform": "place-pktrm", "door-spmnl-nashua": "place-spmnl", "Porter Square": "place-portr", "door-jfk-busway": "place-jfk", "node-cntsq-prospectstair-fareunpaid": "place-cntsq", "node-401-landing": "place-wtcst", "node-395-lobby": "place-aqucl", "node-307-lobby": "place-sull", "node-831-platform": "place-jfk", "Hastings": "place-FR-0137", "node-masta-852-platform": "place-masta", "node-aqucl-nstatestairs-landing": "place-aqucl", "door-kencl-busway": "place-kencl", "node-915-lobby": "place-aqucl", "70257": "place-bckhl", "node-andrw-nobstairs-lobby": "place-andrw", "node-843-busway": "place-forhl", "node-pktrm-midupassstairs-under": "place-pktrm", "Norfolk": "place-FB-0230", "node-863-platform": "place-knncl", "node-aqucl-atlfarepaid": "place-aqucl", "door-matt-southbus": "place-matt", "Natick Center": "place-WML-0177", "70038": "place-bomnl", "node-339-middle": "place-davis", "node-qnctr-crstair-platform": "place-qnctr", "node-forhl-crstairs-lobby": "place-forhl", "door-waban-parkr": "place-waban", "node-nqncy-hstair-street": "place-nqncy", "node-905-platform": "place-haecl", "node-wondl-oceanramp-bottom": "place-wondl", "70141": "place-stplb", "32003": "place-qnctr", "node-knncl-sbmain-fareunpaid": "place-knncl", "node-327-street": "place-nqncy", "70266": "place-butlr", "node-orhte-sara-fareunpaid": "place-orhte", "node-davis-340stair-platform": "place-davis", "door-state-congress": "place-state", "70157": "place-armnl", "37150": "place-ER-0168", "Wellesley Farms-S": "place-WML-0125", "node-crtst-ssexit-farepaid": "place-crtst", "node-402-landing": "place-wtcst", "Needham Junction": "place-NB-0120", "node-harsq-sqhighstair-landing": "place-harsq", "node-310-lobby": "place-welln", "node-880-lobby": "place-andrw", "node-lbusstairs-lower": "place-sull", "node-330-entrance": "place-qnctr", "node-429-lobby": "place-mvbcl", "node-aport-bremenstairs-bridge": "place-aport", "node-712-bridge": "place-orhte", "door-chhil-parke": "place-chhil", "node-sstat-cr-lobby": "place-sstat", "70232": "place-tapst", "node-418-lobby": "place-crtst", "141": "place-alfcl", "node-wondl-footbridgeob": "place-wondl", "node-mvbcl-msqstair-entrance": "place-mvbcl", "node-astao-443-lobby": "place-astao", "node-415-platform": "place-crtst", "door-sstat-summer": "place-sstat", "70015": "place-bbsta", "node-397-landing": "place-aqucl", "node-512-landing": "place-harsq", "door-nqncy-newport": "place-nqncy", "South Station": "place-sstat", "node-knncl-sbsec-farepaid": "place-knncl", "door-newtn-lake": "place-newtn", "node-boyls-in-farepaid": "place-boyls", "door-forhl-upper": "place-forhl", "node-bbsta-olclarexit-bottom": "place-bbsta", "node-brntn-crramp-bottom": "place-brntn", "door-dwnxg-summer": "place-dwnxg", "node-446-bl": "place-gover", "Back Bay-02": "place-bbsta", "node-wlsta-stair7-lobby": "place-wlsta", "node-514-landing": "place-harsq", "node-bbsta-olwstairs-lobby": "place-bbsta", "node-wondl-eplazacenter": "place-wondl", "70131": "place-harvd", "node-fldcr-charlesramp-lobby": "place-fldcr", "node-405-lobby": "place-aqucl", "node-148-lobby": "place-tumnl", "door-rcmnl-tremont": "place-rcmnl", "node-harsq-yardstair-lobby": "place-harsq", "node-crtst-wtcexitstair-platform": "place-crtst", "node-tumnl-tresbstairs-lobby": "place-tumnl", "node-nqncy-sfarepaid": "place-nqncy", "node-800-street": "place-ogmnl", "node-astao-rev-fareunpaid": "place-astao", "door-harsq-yard": "place-harsq", "70057": "place-rbmnl", "Needham Heights": "place-NB-0137", "Plymouth": "place-PB-0356", "node-419-lobby": "place-sstat", "door-grnst-main": "place-grnst", "node-388-lobby": "place-sstat", "node-rugg-bus2stairs-busway": "place-rugg", "node-wtcst-paidlobbycenter": "place-wtcst", "door-mvbcl-square": "place-mvbcl", "node-grnst-farepaid": "place-grnst", "node-709-plaza": "place-wondl", "node-aqucl-atlanticstairs-street": "place-aqucl", "Alewife-02": "place-alfcl", "Chelsea": "place-ER-0046", "door-wlsta-parking": "place-wlsta", "door-newto-unions": "place-newto", "node-pktrm-tremstairfare-unpaid": "place-pktrm", "70044": "place-aqucl", "node-918-sl": "place-sstat", "node-coecl-wbfareunpaid": "place-coecl", "70164": "place-waban", "3125": "place-nqncy", "door-brntn-faregates": "place-brntn", "node-951-lobby": "place-chmnl", "node-bmmnl-379stair-lobby": "place-bmmnl", "door-sstat-bus": "place-sstat", "node-smmnl-953-platform": "place-smmnl", "node-dwnxg-stair6-platform": "place-dwnxg", "Lowell": "place-NHRML-0254", "node-harsq-sqfarepaid": "place-harsq", "door-mlmnl-commercial": "place-mlmnl", "node-hymnl-wbstairs-midtlobby": "place-hymnl", "node-ccmnl-lobby": "place-ccmnl", "node-symcl-wb-fareunpaid": "place-symcl", "door-eliot-lincoln": "place-eliot", "node-dwnxg-stair8-rl": "place-dwnxg", "node-382-lobby": "place-sstat", "North Station-03": "place-north", "node-cntsq-westernstair-platform": "place-cntsq", "node-733-lobby": "place-wlsta", "node-823-under": "place-pktrm", "70211": "place-smary", "node-bomnl-fareunpaid": "place-bomnl", "node-boyls-out-farepaid": "place-boyls", "node-crtst-southentstair-landing": "place-crtst", "door-longw-longwood": "place-longw", "74637": "place-estav", "node-709-street": "place-wondl", "node-971-platform": "place-kencl", "node-140-platform": "place-bbsta", "70036": "place-ogmnl", "node-149-platform": "place-tumnl", "875": "place-forhl", "node-kencl-wbstair-platform": "place-kencl", "70100": "place-wlsta", "door-wtcst-congress": "place-wtcst", "West Roxbury": "place-NB-0080", "node-sstat-919stair-rl": "place-sstat", "node-854-platform": "place-bbsta", "70210": "place-lech", "node-harsq-sbstair-sbn": "place-harsq", "node-bbsta-upper-fareunpaid": "place-bbsta", "node-pktrm-concourse": "place-pktrm", "node-cntsq-pearlstair-farepaid": "place-cntsq", "node-341-platform": "place-davis", "node-harsq-sqfareunpaid": "place-harsq", "20762": "place-harsq", "node-astao-442-ground": "place-astao", "door-qamnl-burgin": "place-qamnl", "74611": "place-sstat", "node-coecl-wbfarepaid": "place-coecl", "Four Corners / Geneva": "place-DB-2249", "door-dwnxg-summereast": "place-dwnxg", "74633": "place-belsq", "JFK/UMASS": "place-jfk", "node-wlsta-stair7-street": "place-wlsta", "70152": "place-hymnl", "node-crtst-ssmain-farepaid": "place-crtst", "node-rcmnl-stairs-lobby": "place-rcmnl", "Norfolk-S": "place-FB-0230", "node-aport-buses-fareunpaid": "place-aport", "node-hymnl-fareunpaid": "place-hymnl", "node-orhte-ibpaidstairs-platform": "place-orhte", "node-445-lobby": "place-gover", "node-151-lobby": "place-prmnl", "node-andrw-sibingress": "place-andrw", "node-bomnl-lobstair-entrance": "place-bomnl", "node-tumnl-washsbstairs-lobby": "place-tumnl", "node-mvbcl-lewstair-entrance": "place-mvbcl", "5880": "place-orhte", "29012": "place-sull", "node-knncl-backnbstair-entrance": "place-knncl", "door-longw-colchester": "place-longw", "door-pktrm-exitashbrain": "place-pktrm", "node-aqucl-wbatlanticstairs-platform": "place-aqucl", "node-harsq-churstair-lobby": "place-harsq", "node-masta-139-lobby": "place-masta", "57400": "place-mvbcl", "node-pktrm-stair5-rl": "place-pktrm", "Manchester": "place-GB-0254", "River Works / GE Employees Only": "place-ER-0099", "node-armnl-eescstairs-lobby": "place-armnl", "899": "place-kencl", "node-867-lobby": "place-brdwy", "node-bbsta-e57stairs-platform": "place-bbsta", "node-mlmnl-ramptop": "place-mlmnl", "node-441-bridge": "place-orhte", "Concord": "place-FR-0201", "node-sstat-bldgescup-lobby": "place-sstat", "70251": "place-fenwd", "Bridgewater": "place-MM-0277", "door-miltt-trail": "place-miltt", "node-955-bridge": "place-aport", "node-432-platform": "place-kencl", "node-sbmnl-132-platform": "place-sbmnl", "70245": "place-mfa", "node-asmnl-radfordramp": "place-asmnl", "node-377-landing": "place-chncl", "node-mlmnl-crstairs-lobby": "place-mlmnl", "70127": "place-alsgr", "door-armnl-arltw": "place-armnl", "node-armnl-swstairs-lobby": "place-armnl", "door-kencl-commonwealth": "place-kencl", "node-asmnl-rdexstair-lobby": "place-asmnl", "70273": "place-capst", "node-forhl-crstairs-platform": "place-forhl", "node-800-crplatform": "place-ogmnl", "node-141-lobby": "place-bbsta", "node-astao-717-lobby": "place-astao", "Wachusett": "place-FR-3338", "Holbrook/ Randolph": "place-MM-0150", "node-boyls-in-fareunpaid": "place-boyls", "node-701-plaza": "place-wondl", "West Newton": "place-WML-0091", "Boston Landing": "place-WML-0035", "node-bbsta-clar-fareunpaid": "place-bbsta", "door-newto-herrick": "place-newto", "Mishawum": "place-NHRML-0116", "node-brdwy-travelerstairs-lobby": "place-brdwy", "node-kencl-fvmstair-landing": "place-kencl", "node-979-gl": "place-pktrm", "node-444-platform": "place-gover", "323": "place-fldcr", "node-339-lobby": "place-davis", "node-haecl-congogstairs-passage": "place-haecl", "node-astao-718-ground": "place-astao", "node-forhl-busfareunpaid": "place-forhl", "node-ogmnl-olstair-platform": "place-ogmnl", "Wellesley Square-S": "place-WML-0147", "node-forhl-nlowbusstairs-busway": "place-forhl", "node-410-bridge": "place-aport", "node-955-lobby": "place-aport", "Wyoming Hill": "place-WR-0062", "Greenbush": "place-GRB-0276", "node-812-under": "place-pktrm", "node-733-bridge": "place-wlsta", "node-407-bridge": "place-aport", "door-pktrm-exitalewife": "place-pktrm", "node-symcl-hunestair-platform": "place-symcl", "Malden Center": "place-mlmnl", "node-431-lobby": "place-kencl", "door-coecl-east": "place-coecl", "17861": "place-rugg", "node-wimnl-ibunpaidstairs-bridge": "place-wimnl", "node-aqucl-nstatestairs-street": "place-aqucl", "node-asmnl-mtpnbstair-lobby": "place-asmnl", "70183": "place-longw", "node-chncl-ogupper-landing": "place-chncl", "Melrose Cedar Park": "place-WR-0067", "node-armnl-fareunpaid": "place-armnl", "node-wimnl-love-fareunpaid": "place-wimnl", "70196": "place-pktrm", "door-miltt-wharf": "place-miltt", "node-crtst-ssmainstair-platform": "place-crtst", "node-jfk-oldstairw-lobby": "place-jfk", "node-gover-nentrancestairs-lobby": "place-gover", "node-prmnl-921stair-platform": "place-prmnl", "node-crtst-ssexitstair-platform": "place-crtst", "node-asmnl-radfareunpaid": "place-asmnl", "node-448-bridge": "place-wlsta", "node-340-platform": "place-davis", "door-wondl-revere": "place-wondl", "node-kencl-fvmramp-landing": "place-kencl", "70075": "place-pktrm", "door-brntn-busway": "place-brntn", "door-bvmnl-kent": "place-bvmnl", "node-rugg-bus2stairs-lobby": "place-rugg", "node-wimnl-obpaidstairs-bridge": "place-wimnl", "node-901-rl": "place-sstat", "node-bbsta-2stairs-lobby": "place-bbsta", "121": "place-jfk", "node-dwnxg-macysstairs-lobby": "place-dwnxg", "door-knncl-nbsecond": "place-knncl", "node-dwnxg-stair15-lobby": "place-dwnxg", "node-322-lobby": "place-jfk", "70156": "place-armnl", "door-brdwy-traveler": "place-brdwy", "node-grnst-131-lobby": "place-grnst", "node-crtst-wtcmainstair-platform": "place-crtst", "node-mlmnl-commstair-bus": "place-mlmnl", "node-925-lobby": "place-aqucl", "node-symcl-wb-midtop": "place-symcl", "node-jfk-bragasstair-platform": "place-jfk", "node-asmnl-peanbstair-lobby": "place-asmnl", "70050": "place-wimnl", "node-311-lobby": "place-mlmnl", "door-davis-holland": "place-davis", "node-sstat-400sl-sl": "place-sstat", "node-chmnl-nbstairs-lobby": "place-chmnl", "node-astao-718-lobby": "place-astao", "node-forhl-nplatstairs-lobby": "place-forhl", "node-wtcst-wtctstairs-landing": "place-wtcst", "node-130-platform": "place-forhl", "node-429-entrance": "place-mvbcl", "node-wlsta-stair6gate-farepaid": "place-wlsta", "door-ogmnl-banks": "place-ogmnl", "South Station-06": "place-sstat", "node-gover-sentrancestairs-lobby": "place-gover", "Forest Hills-02": "place-forhl", "70229": "place-bcnwa", "door-fenwy-parkdr": "place-fenwy", "node-crtst-ssmain-fareunpaid": "place-crtst", "38155": "place-river", "node-davis-341stair-lobby": "place-davis", "17863": "place-rugg", "node-720-platform": "place-gover", "334": "place-asmnl", "node-843-lobby": "place-forhl", "node-859-lobby": "place-tumnl", "node-963-platform": "place-armnl", "node-444-lobby": "place-gover", "node-309-lobby": "place-welln", "node-wondl-oceanaveingress": "place-wondl", "North Wilmington": "place-WR-0163", "node-harsq-lowerramp-lobby": "place-harsq", "node-440-bridge": "place-orhte", "node-914-platform": "place-aqucl", "door-cntsq-essex": "place-cntsq", "node-720-lobby": "place-gover", "node-masta-139-platform": "place-masta", "node-361-platform": "place-knncl", "node-864-lobby": "place-welln", "node-wimnl-love-stairs": "place-wimnl", "node-934-lobby": "place-wtcst", "door-bomnl-main": "place-bomnl", "13": "place-andrw", "70226": "place-bndhl", "70275": "place-matt", "door-spmnl-obrien": "place-spmnl", "70247": "place-lngmd", "node-spmnl-mfarepaid": "place-spmnl", "node-130-lobby": "place-forhl", "node-332-ol": "place-dwnxg", "node-pktrm-nbexitunpaid": "place-pktrm", "node-721-platform": "place-gover", "node-wondl-obplatstairs-platform": "place-wondl", "node-andrw-farepaid": "place-andrw", "node-pktrm-stair14-rl": "place-pktrm", "door-north-crcanal": "place-north", "door-portr-cracross": "place-portr", "node-402-lobby": "place-wtcst", "node-asmnl-peafareunpaid": "place-asmnl", "74635": "place-boxdt", "70083": "place-andrw", "node-722-gl": "place-gover", "node-711-plaza": "place-wondl", "node-hymnl-ebstairs-platform": "place-hymnl", "70092": "place-smmnl", "node-dwnxg-stair5-lobby": "place-dwnxg", "node-haecl-busfarepaid": "place-haecl", "node-dwnxg-wintwashfare-paid": "place-dwnxg", "node-863-entrance": "place-knncl", "door-shmnl-sydney": "place-shmnl", "70086": "place-jfk", "node-crtst-southlobstair-landing": "place-crtst", "door-aqucl-mcksouth": "place-aqucl", "node-830-platform": "place-jfk", "node-knncl-sbsec-fareunpaid": "place-knncl", "node-tumnl-wash-farepaid": "place-tumnl", "door-qnctr-busway": "place-qnctr", "door-eliot-boylws": "place-eliot", "node-428-entrance": "place-mvbcl", "node-masta-camfarepaid": "place-masta", "node-145-lobby": "place-tumnl", "node-wondl-nshoreplazastairs-street": "place-wondl", "node-bbsta-lower-fareunpaid": "place-bbsta", "node-137-platform": "place-rugg", "door-newto-langley": "place-newto", "node-prmnl-prustair-street": "place-prmnl", "node-sstat-south-farepaid": "place-sstat", "node-897-lobby": "place-nqncy", "node-420-rl": "place-sstat", "door-north-tdgarden": "place-north", "node-wondl-oceanstairs-plaza": "place-wondl", "29013": "place-sull", "node-rcmnl-farepaid": "place-rcmnl", "70114": "place-chswk", "70261": "place-asmnl", "door-welln-garage": "place-welln", "door-pktrm-elevatorwb": "place-pktrm", "node-958-lobby": "place-fldcr", "door-symcl-ebsymphony": "place-symcl", "node-842-lobby": "place-forhl", "Quincy Center": "place-qnctr", "node-jfk-ashganstair-lobby": "place-jfk", "Endicott": "place-FB-0109", "node-crtst-ssmainstair-lobby": "place-crtst", "door-sstat-main": "place-sstat", "node-knncl-sbmain-farepaid": "place-knncl", "node-mlmnl-exitfarepaid": "place-mlmnl", "node-nqncy-nhpstair-lobby": "place-nqncy", "node-symcl-wb-midbottom": "place-symcl", "node-boyls-out-fareunpaid": "place-boyls", "node-889-paidbridge": "place-wimnl", "door-chhil-parkw": "place-chhil", "door-symcl-westland": "place-symcl", "node-104-lobby": "place-ogmnl", "node-harsq-sbstair-sbs": "place-harsq", "North Leominster": "place-FR-0451", "Middleborough/ Lakeville": "place-MM-0356", "70167": "place-eliot", "node-ccmnl-fareunpaid": "place-ccmnl", "Southborough": "place-WML-0274", "node-wlsta-mainnewp-fareunpaid": "place-wlsta", "node-cntsq-ibstair-platform": "place-cntsq", "70239": "place-prmnl", "node-haecl-passogstair-passage": "place-haecl", "door-dwnxg-rochebros": "place-dwnxg", "node-welln-fhstair-lobby": "place-welln", "node-jfk-bracolstair-lobby": "place-jfk", "node-aport-bremen-farepaid": "place-aport", "door-portr-crtransfer": "place-portr", "Ballardvale": "place-WR-0205", "door-fldcr-charles": "place-fldcr", "Hyde Park": "place-NEC-2203", "node-817-lobby": "place-davis", "Newtonville": "place-WML-0081", "node-152-platform": "place-prmnl", "node-davis-340stair-lobby": "place-davis", "70142": "place-buwst", "node-cntsq-ibstair-farepaid": "place-cntsq", "node-rugg-fareunpaid": "place-rugg", "node-astao-fol-farepaid": "place-astao", "node-crtst-northentstair-entrance": "place-crtst", "node-435-lobby": "place-armnl", "Weymouth Landing/ East Braintree": "place-GRB-0118", "East Weymouth": "place-GRB-0146", "node-wondl-buswaydoor": "place-wondl", "node-kencl-fareunpaid": "place-kencl", "70110": "place-sougr", "node-sstat-bldgescup-ground": "place-sstat", "node-welln-busramp-lobby": "place-welln", "70170": "place-newto", "70121": "place-wascm", "node-900-platform": "place-nqncy", "node-412-lobby": "place-crtst", "70066": "place-portr", "node-spmnl-ibstairs-platform": "place-spmnl", "node-jfk-ashcolfareunpaid": "place-jfk", "node-382-rl": "place-sstat", "node-448-lobby": "place-wlsta", "node-325-lobby": "place-nqncy", "node-masta-mainstair-lobby": "place-masta", "node-astao-719-platform": "place-astao", "70035": "place-mlmnl", "node-853-lobby": "place-bbsta", "70003": "place-grnst", "node-dwnxg-wintexitfare-unpaid": "place-dwnxg", "node-brntn-nplatstairs-platform": "place-brntn", "node-wlsta-stair6-lobby": "place-wlsta", "node-pktrm-wbparkstairs-lobby": "place-pktrm", "70008": "place-rcmnl", "node-905-passage": "place-haecl", "Wellesley Hills": "place-WML-0135", "Haverhill": "place-WR-0329", "node-rugg-crstairs-platform": "place-rugg", "door-valrd-eliot": "place-valrd", "node-astao-fol-fareunpaid": "place-astao", "node-dwnxg-113fare-paid": "place-dwnxg", "node-340-lobby": "place-davis", "South Station-09": "place-sstat", "node-jfk-ashsydstair-platform": "place-jfk", "node-kencl-ebstair-lobby": "place-kencl", "node-414-lobby": "place-crtst", "Auburndale": "place-WML-0102", "node-327-lobby": "place-nqncy", "node-bomnl-ramp-platform": "place-bomnl", "70117": "place-sthld", "node-harsq-lowupstair-lower": "place-harsq", "node-855-platform": "place-bbsta", "node-wtcst-wtcbstairs-landing": "place-wtcst", "node-703-plaza": "place-wondl", "70102": "place-qnctr", "door-aqucl-atlantic": "place-aqucl", "node-703-bridge": "place-wondl", "node-901-lobby": "place-sstat", "node-409-bridge": "place-aport", "node-shmnl-endstair-lobby": "place-shmnl", "node-999-ol": "place-dwnxg", "Natick Center-S": "place-WML-0177", "70173": "place-chhil", "node-haecl-busstair-lobby": "place-haecl", "node-425-platform": "place-chmnl", "node-tumnl-tresbstairs-platform": "place-tumnl", "node-pktrm-cpebstairs-gl": "place-pktrm", "node-sstat-south-fareunpaid": "place-sstat", "node-102-street": "place-ogmnl", "node-astao-revdoorstair-lobby": "place-astao", "70041": "place-state", "node-welln-skyelev-bridge": "place-welln", "node-symcl-eb-midtop": "place-symcl", "node-shmnl-platstair-lobby": "place-shmnl", "node-sstat-bldgescdown-ground": "place-sstat", "node-406-lobby": "place-aqucl", "node-harsq-lowerstair-lobby": "place-harsq", "node-dwnxg-sbsumexitfare-unpaid": "place-dwnxg", "29001": "place-sull", "node-bomnl-entstair": "place-bomnl", "node-symcl-eb-fareunpaid": "place-symcl", "node-841-platform": "place-forhl", "74614": "place-conrd", "node-945-lobby": "place-mlmnl", "node-pktrm-stair14-gl": "place-pktrm", "Hanson": "place-PB-0245", "Lincoln": "place-FR-0167", "node-jaksn-846-lobby": "place-jaksn", "node-715-street": "place-orhte", "70126": "place-alsgr", "Wakefield": "place-WR-0099", "node-wlsta-newpramp-lobby": "place-wlsta", "South Station-11": "place-sstat", "node-nqncy-nstair-lobby": "place-nqncy", "node-rcmnl-847-lobby": "place-rcmnl", "door-pktrm-west": "place-pktrm", "door-mlmnl-pleasant": "place-mlmnl", "South Station-04": "place-sstat", "Belmont": "place-FR-0064", "node-nqncy-spstair-lobby": "place-nqncy", "node-914-lobby": "place-aqucl", "node-wlsta-stair1-lobby": "place-wlsta", "door-armnl-elevator": "place-armnl", "door-jfk-sydneys": "place-jfk", "70033": "place-welln", "70242": "place-symcl", "node-927-rl": "place-sstat", "door-fenwy-longwood": "place-fenwy", "node-jfk-sydneysstair-lobby": "place-jfk", "node-cntsq-westernstair-fareunpaid": "place-cntsq", "node-415-lobby": "place-crtst", "node-413-entrance": "place-crtst", "node-431-platform": "place-kencl", "Hamilton/ Wenham": "place-ER-0227", "door-nqncy-hancock": "place-nqncy", "door-bbsta-clarendon1": "place-bbsta", "door-butlr-bearse": "place-butlr", "door-rugg-forsyth": "place-rugg", "node-armnl-sestairs-lobby": "place-armnl", "node-125-entrance": "place-bomnl", "node-wondl-lobbycenter": "place-wondl", "70042": "place-state", "node-andrw-obelstairs-lobby": "place-andrw", "70140": "place-stplb", "door-wtcst-wtc": "place-wtcst", "node-919-rl": "place-sstat", "70074": "place-chmnl", "node-andrw-ibramp-top": "place-andrw", "node-orhte-ibpaidstairs-bridge": "place-orhte", "node-pktrm-tremontstairs-lobby": "place-pktrm", "North Station-08": "place-north", "node-cntsq-860-platform": "place-cntsq", "node-ogmnl-fareunpaid": "place-ogmnl", "node-orhte-obunpaidstairs-street": "place-orhte", "node-401-top": "place-wtcst", "70203": "place-haecl", "door-andrw-exitonly": "place-andrw", "node-spmnl-nfareunpaid": "place-spmnl", "door-jaksn-main": "place-jaksn", "Wellesley Hills-S": "place-WML-0135", "door-boyls-inbound": "place-boyls", "node-kencl-wbstair-lobby": "place-kencl", "Kendal Green": "place-FR-0132", "door-rsmnl-wstairs": "place-rsmnl", "node-sstat-388stair-sl": "place-sstat", "70017": "place-tumnl", "70838": "place-bomnl", "node-masta-camdstair-platform": "place-masta", "70159": "place-boyls", "23391": "place-bbsta", "70153": "place-hymnl", "Braintree-02": "place-brntn", "node-rugg-olexit-fareunpaid": "place-rugg", "door-wimnl-benning": "place-wimnl", "70098": "place-nqncy", "node-515-landing": "place-harsq", "70105": "place-brntn", "North Station-04": "place-north", "70216": "place-kntst", "15795": "place-wondl", "door-chmnl-main": "place-chmnl", "70055": "place-bmmnl", "70099": "place-wlsta", "node-dwnxg-nbsumexitfare-paid": "place-dwnxg", "70165": "place-waban", "node-965-lobby": "place-mvbcl", "door-bvmnl-washington": "place-bvmnl", "door-matt-northbus": "place-matt", "door-wlsta-newpnorth": "place-wlsta", "node-331-ol": "place-dwnxg", "node-940-lobby": "place-crtst", "node-haecl-passogstair-platform": "place-haecl", "door-dwnxg-winter": "place-dwnxg", "node-969-lobby": "place-asmnl", "node-898-street": "place-nqncy", "node-972-paidlobby": "place-kencl", "node-899-platform": "place-nqncy", "70149": "place-bland", "node-masta-camfareunpaid": "place-masta", "node-symcl-hunwstair-platform": "place-symcl", "node-pktrm-wintfare-paid": "place-pktrm", "70230": "place-bcnwa", "70054": "place-sdmnl", "door-alfcl-russell": "place-alfcl", "node-brntn-farepaid": "place-brntn", "door-mlmnl-ramp": "place-mlmnl", "door-masta-corridor": "place-masta", "Morton Street": "place-DB-2230", "node-714-platform": "place-orhte", "node-913-platform": "place-aqucl", "node-symcl-weststair-platform": "place-symcl", "node-hymnl-newburyexit": "place-hymnl", "70005": "place-sbmnl", "node-asmnl-mtpfareunpaid": "place-asmnl", "node-404-platform": "place-wtcst", "door-pktrm-elevatoreb": "place-pktrm", "node-513-landing": "place-harsq", "70135": "place-brico", "node-722-bl": "place-gover", "node-aqucl-atlanticstairs-lobby": "place-aqucl", "node-prmnl-huntstair-lobby": "place-prmnl", "door-jfk-sydneyn": "place-jfk", "door-haecl-busway": "place-haecl", "53270": "place-mlmnl", "node-jfk-mainfareunpaid": "place-jfk", "node-dwnxg-stair14-lobby": "place-dwnxg", "70002": "place-grnst", "node-425-lobby": "place-chmnl", "node-harsq-sqlowstair-landing": "place-harsq", "node-364-lobby": "place-dwnxg", "node-hymnl-ebstairs-lobby": "place-hymnl", "node-wondl-plazacenter": "place-wondl", "node-734-lobby": "place-wlsta", "door-woodl-east": "place-woodl", "node-prmnl-ebstair-platform": "place-prmnl", "node-966-entrance": "place-mvbcl", "node-rugg-olsstairs-lobby": "place-rugg", "door-orhte-benning": "place-orhte", "door-cenav-mattapan": "place-cenav", "node-kencl-ebstair-platform": "place-kencl", "node-sstat-bldgstair-lobby": "place-sstat", "70244": "place-nuniv", "node-dwnxg-frnkfare-unpaid": "place-dwnxg", "70172": "place-chhil", "Ruggles-01": "place-rugg", "door-rsmnl-estairs": "place-rsmnl", "node-prmnl-fareunpaid": "place-prmnl", "node-welln-busstair-lobby": "place-welln", "node-brntn-splatstairs-platform": "place-brntn", "Ashland": "place-WML-0252", "node-876-lobby": "place-chncl", "node-haecl-congogstairn-lobby": "place-haecl", "node-150-lobby": "place-prmnl", "node-sull-farepaid": "place-sull", "Rowley": "place-ER-0312", "70186": "place-fenwy", "70198": "place-pktrm", "node-asmnl-peafarepaid": "place-asmnl", "node-6476-ground": "place-sstat", "70139": "place-plsgr", "door-newtn-walnut": "place-newtn", "node-sstat-388stair-lobby": "place-sstat", "70016": "place-tumnl", "node-wlsta-lobbysteps-upper": "place-wlsta", "node-146-platform": "place-tumnl", "node-forhl-nlowbusstairs-lobby": "place-forhl", "node-936-platform": "place-wtcst", "node-972-platform": "place-kencl", "node-sstat-382stair-lobby": "place-sstat", "node-315-top": "place-hymnl", "70254": "place-mispk", "door-symcl-falmouth": "place-symcl", "node-938-platform": "place-crtst", "node-mvbcl-msqfareunpaid": "place-mvbcl", "node-gover-sentrancestairs-platform": "place-gover", "node-dwnxg-stair4-lobby": "place-dwnxg", "node-forhl-nplatstairs-platform": "place-forhl", "node-956-lobby": "place-aport", "Brockton": "place-MM-0200", "door-miltt-adams": "place-miltt", "node-889-paidplatform": "place-wimnl", "node-sstat-389stair-rl": "place-sstat", "node-936-lobby": "place-wtcst", "node-998-ol": "place-dwnxg", "node-harsq-harstair-platform": "place-harsq", "node-949-lobby": "place-sstat", "70264": "place-cedgr", "70014": "place-bbsta", "node-asmnl-rdexstair-platform": "place-asmnl", "node-crtst-wtcexit-fareunpaid": "place-crtst", "node-367-platform": "place-brdwy", "node-wlsta-mainnewp-farepaid": "place-wlsta", "node-hymnl-wbstairs-midblobby": "place-hymnl", "node-135-lobby": "place-rugg", "door-longw-necklace": "place-longw", "node-haecl-busfareunpaid": "place-haecl", "node-dwnxg-templefare-paid": "place-dwnxg", "node-399-lobby": "place-sstat", "node-310-platform": "place-welln", "node-pktrm-weststairs-lobby": "place-pktrm", "node-735-platform": "place-wlsta", "node-389-lobby": "place-sstat", "door-wondl-oceannele": "place-wondl", "node-lech-fareunpaid": "place-lech", "node-865-lobby": "place-welln", "node-haecl-congfhplats-platform": "place-haecl", "node-388-sl": "place-sstat", "node-144-lobby": "place-bbsta", "70039": "place-gover", "node-masta-852-lobby": "place-masta", "70148": "place-bland", "node-841-lobby": "place-forhl", "node-aport-buswaystairs-bridge": "place-aport", "node-dwnxg-stair1-rl": "place-dwnxg", "5072": "place-mlmnl", "node-wlsta-stair6-platform": "place-wlsta", "70093": "place-asmnl", "node-963-lobby": "place-armnl", "node-bbsta-upassmezstairs-top": "place-bbsta", "node-andrw-sibstairs-platform": "place-andrw", "node-891-lobby": "place-dwnxg", "node-721-lobby": "place-gover", "node-rcmnl-847-platform": "place-rcmnl", "70045": "place-mvbcl", "node-chncl-ogonlystair-lobby": "place-chncl", "node-mvbcl-lewstair-lobby": "place-mvbcl", "node-712-platform": "place-orhte", "Dedham Corp Center-S": "place-FB-0118", "node-409-platform": "place-aport", "70212": "place-smary", "node-qnctr-burgin-door": "place-qnctr", "node-sbmnl-farepaid": "place-sbmnl", "70278": "place-astao", "node-crtst-ssexit-fareunpaid": "place-crtst", "29010": "place-sull", "node-wimnl-obunpaidstairs-bridge": "place-wimnl", "node-979-rl": "place-pktrm", "node-crtst-wtcmainstair-lobby": "place-crtst", "door-chncl-ogelevator": "place-chncl", "Foxboro": "place-FS-0049", "node-414-platform": "place-crtst", "door-asmnl-peabody": "place-asmnl", "node-rugg-olexit-farepaid": "place-rugg", "node-wtcst-wtcbstairs-lobby": "place-wtcst", "node-masta-farepaid": "place-masta", "Montello": "place-MM-0186", "door-alfcl-cambridgepark": "place-alfcl", "South Station-S": "place-sstat", "71150": "place-kencl", "door-cedgr-fellsway": "place-cedgr", "door-bbsta-dartms": "place-bbsta", "node-pktrm-wbupassstairs-under": "place-pktrm", "node-812-platform": "place-pktrm", "node-jfk-crcolstair-street": "place-jfk", "node-brntn-splatstairs-lobby": "place-brntn", "door-masta-camden": "place-masta", "node-937-lobby": "place-crtst", "door-bcnfd-dean": "place-bcnfd", "Plimptonville": "place-FB-0177", "70130": "place-harvd", "node-pktrm-westfare-unpaid": "place-pktrm", "node-326-platform": "place-nqncy", "node-qnctr-crstair-entrance": "place-qnctr", "door-capst-mattapan": "place-capst", "node-pktrm-stair4-lobby": "place-pktrm", "door-andrw-busway": "place-andrw", "70175": "place-rsmnl", "node-andrw-nbusstairs-lobby": "place-andrw", "70223": "place-sumav", "node-wtcst-obstairs-platform": "place-wtcst", "70001": "place-forhl", "node-pktrm-stair17-lobby": "place-pktrm", "11531": "place-jaksn", "node-haecl-passfhstair-passage": "place-haecl", "70233": "place-denrd", "node-asmnl-mtpnbstair-platform": "place-asmnl", "South Station-01": "place-sstat", "node-coecl-976-platform": "place-coecl", "Forge Park / 495": "place-FB-0303", "Readville-S": "place-DB-0095", "door-hymnl-mass": "place-hymnl", "node-wlsta-newprampup-middle": "place-wlsta", "Yawkey": "place-WML-0025", "door-haecl-congress": "place-haecl", "South Station-03": "place-sstat", "70143": "place-buwst", "70150": "place-kencl", "Dedham Corp Center": "place-FB-0118", "node-jfk-ashcolfarepaid": "place-jfk", "South Station-08": "place-sstat", "node-bomnl-pstair-lobby": "place-bomnl", "70081": "place-brdwy", "node-438-platform": "place-asmnl", "Abington": "place-PB-0194", "node-840-lobby": "place-sull", "node-rugg-forsythstairs-bottom": "place-rugg", "Salem": "place-ER-0168", "door-north-causewaye": "place-north", "node-astao-719-lobby": "place-astao", "node-dwnxg-macysramp-lobby": "place-dwnxg", "node-bbsta-w57stairs-platform": "place-bbsta", "node-wondl-obplazaentrance": "place-wondl", "node-361-entrance": "place-knncl", "18511": "place-matt", "node-davis-colstairup-middle": "place-davis", "node-301-platform": "place-andrw", "node-981-platform": "place-spmnl", "node-sstat-420sl-sl": "place-sstat", "door-wimnl-lovell": "place-wimnl", "node-dwnxg-templefare-unpaid": "place-dwnxg", "node-bmmnl-farepaid": "place-bmmnl", "node-957-platform": "place-fldcr", "node-grnst-stairs-lobby": "place-grnst", "node-124-platform": "place-andrw", "door-eliot-boyle": "place-eliot", "door-coecl-bpl": "place-coecl", "door-waban-wyman": "place-waban", "node-harsq-lowerramp-lower": "place-harsq", "node-bomnl-ramp-lobby": "place-bomnl", "70058": "place-rbmnl", "node-prmnl-ebstair-lobby": "place-prmnl", "node-338-middle": "place-davis", "node-sull-nbstairs-lobby": "place-sull", "70077": "place-dwnxg", "70048": "place-aport", "70090": "place-fldcr", "node-nqncy-nhfarepaid": "place-nqncy", "node-wlsta-park-farepaid": "place-wlsta", "node-dwnxg-stair1-ol": "place-dwnxg", "node-417-platform": "place-crtst", "node-brntn-crstairs-top": "place-brntn", "node-spmnl-ofareunpaid": "place-spmnl", "node-703-lobby": "place-wondl", "node-knncl-frontsbstair-entrance": "place-knncl", "node-wtcst-wtctstairs-top": "place-wtcst", "70268": "place-miltt", "door-rugg-buses": "place-rugg", "74632": "place-belsq", "node-372-lobby": "place-brdwy", "Forge Park / 495-S": "place-FB-0303", "door-bcnfd-clark": "place-bcnfd", "node-jfk-ashcolstair-lobby": "place-jfk", "5666": "place-wimnl", "Norwood Central-S": "place-FB-0148", "node-880-platform": "place-andrw", "node-wtcst-obstairs-lobby": "place-wtcst", "node-chncl-fhfarepaid": "place-chncl", "node-tumnl-washstairs-lobby": "place-tumnl", "door-spmnl-nashuael": "place-spmnl", "node-welln-fareunpaid": "place-welln", "Rockport": "place-GB-0353", "node-rugg-columbusstairs-top": "place-rugg", "Nantasket Junction": "place-GRB-0183", "node-331-rl": "place-dwnxg", "Canton Junction": "place-NEC-2139", "node-516-platform": "place-harsq", "door-sbmnl-main": "place-sbmnl", "Walpole": "place-FB-0191", "17862": "place-rugg", "node-davis-colstairlow-middle": "place-davis", "node-396-landing": "place-aqucl", "Back Bay-05": "place-bbsta", "node-mvbcl-lewfareunpaid": "place-mvbcl", "West Hingham": "place-GRB-0162", "node-welln-farepaid": "place-welln", "node-orhte-benn-farepaid": "place-orhte", "70022": "place-state", "node-kencl-farepaid": "place-kencl", "node-spmnl-nfarepaid": "place-spmnl", "node-378-platform": "place-bmmnl", "node-orhte-obpaidstairs-bridge": "place-orhte", "node-313-lobby": "place-haecl", "door-symcl-hunte": "place-symcl", "node-haecl-congogstairn-passage": "place-haecl", "node-404-lobby": "place-wtcst", "node-kencl-fvmstair-lobby": "place-kencl", "node-896-entrance": "place-qnctr", "node-davis-holland-lobby": "place-davis", "29006": "place-sull", "Reading": "place-WR-0120", "node-395-platform": "place-aqucl", "node-pktrm-nbwinterstairs-lobby": "place-pktrm", "node-ccmnl-stairs-platform": "place-ccmnl", "4255": "place-MM-0150", "node-713-bridge": "place-orhte", "door-pktrm-tremontw": "place-pktrm", "node-cntsq-essexstair-fareunpaid": "place-cntsq", "node-andrw-dotstairs-lobby": "place-andrw", "node-980-street": "place-spmnl", "node-astao-443-platform": "place-astao", "door-waban-parks": "place-waban", "node-wtcst-fareunpaid": "place-wtcst", "node-918-lobby": "place-sstat", "node-fldcr-fareunpaid": "place-fldcr", "70010": "place-rugg", "node-mlmnl-exitfareunpaid": "place-mlmnl", "node-symcl-sympstair-platform": "place-symcl", "70182": "place-longw", "door-kencl-beacon": "place-kencl", "70106": "place-lake", "node-andrw-sbusstairs-lobby": "place-andrw", "node-andrw-nibstairs-platform": "place-andrw", "door-sstat-usps": "place-sstat", "70025": "place-haecl", "node-918-rl": "place-sstat", "node-cntsq-359-platform": "place-cntsq", "node-haecl-busolstair-passage": "place-haecl", "70034": "place-mlmnl", "door-state-water": "place-state", "Ayer": "place-FR-0361", "node-aqucl-nstatestairs-lobby": "place-aqucl", "door-qamnl-indep": "place-qamnl", "Beverly Farms": "place-GB-0229", "node-coecl-bplstair-platform": "place-coecl", "70112": "place-chill", "70187": "place-fenwy", "node-399-middle": "place-sstat", "node-brdwy-platstairs-lobby": "place-brdwy", "door-waban-beacon": "place-waban", "70217": "place-stpul", "node-bbsta-13clarexit-farepaid": "place-bbsta", "Attleboro": "place-NEC-1969", "door-bbsta-busways": "place-bbsta", "node-jfk-braganstair-platform": "place-jfk", "node-wondl-busramp-busway": "place-wondl", "node-wimnl-obpaidstairs-platform": "place-wimnl", "71199": "place-pktrm", "node-jfk-crramp-street": "place-jfk", "node-rugg-farepaid": "place-rugg", "node-wondl-ibplazastairs-top": "place-wondl", "node-prmnl-920ramp-platform": "place-prmnl", "node-973-upper": "place-harsq", "node-441-platform": "place-orhte", "door-newto-braeland": "place-newto", "Highland": "place-NB-0076", "door-pktrm-tremonte": "place-pktrm", "Ruggles-03": "place-rugg", "node-817-entrance": "place-davis", "South Station-10": "place-sstat", "South Weymouth": "place-PB-0158", "node-sstat-390stair-sl": "place-sstat", "node-808-rl": "place-pktrm", "node-tumnl-washnbstairs-lobby": "place-tumnl", "Norwood Central": "place-FB-0148", "node-haecl-busolstair-green": "place-haecl", "node-pktrm-cpwbstairs-gl": "place-pktrm", "node-haecl-congogplats-passage": "place-haecl", "70026": "place-north", "node-373-platform": "place-pktrm", "node-147-lobby": "place-tumnl", "node-bbsta-dartexit-fareunpaid": "place-bbsta", "node-pktrm-ebupassstairs-platform": "place-pktrm", "node-952-lobby": "place-chmnl", "node-702-plaza": "place-wondl", "node-ogmnl-olstair-lobby": "place-ogmnl", "29002": "place-sull", "node-aqucl-wbstatestairs-lobby": "place-aqucl", "Littleton / Rte 495": "place-FR-0301", "Providence": "place-NEC-1851", "node-366-lobby": "place-chncl", "node-bbsta-13clarexit-fareunpaid": "place-bbsta", "node-407-platform": "place-aport", "node-ccmnl-305-lobby": "place-ccmnl", "node-881-lobby": "place-sull", "node-haecl-glstair-passage": "place-haecl", "node-383-street": "place-nqncy", "node-pktrm-ebupassstairs-under": "place-pktrm", "node-cntsq-360-platform": "place-cntsq", "node-128-lobby": "place-forhl", "70088": "place-shmnl", "node-935-lobby": "place-wtcst", "node-417-lobby": "place-crtst", "node-403-platform": "place-wtcst", "door-river-main": "place-river", "8310": "place-haecl", "Framingham": "place-WML-0214", "70082": "place-brdwy", "node-wondl-busstairs-busway": "place-wondl", "node-337-entrance": "place-davis", "node-jfk-sydfarepaid": "place-jfk", "node-jfk-bracolfarepaid": "place-jfk", "node-dwnxg-sbsumexitfare-paid": "place-dwnxg", "node-734-platform": "place-wlsta", "70147": "place-buest", "node-armnl-ebstairs-platform": "place-armnl", "node-bbsta-e57stairs-lobby": "place-bbsta", "70004": "place-sbmnl", "node-881-platform": "place-sull", "node-harsq-lowupstair-upper": "place-harsq", "70168": "place-newtn", "node-mlmnl-fareunpaid": "place-mlmnl", "node-brntn-crstairs-bottom": "place-brntn", "node-801-lobby": "place-ogmnl", "70094": "place-asmnl", "node-dwnxg-nbsumexitfare-unpaid": "place-dwnxg", "Beverly": "place-ER-0183", "node-cntsq-essexstair-platform": "place-cntsq", "node-sstat-reservestair-lobby": "place-sstat", "node-419-middle": "place-sstat", "node-hymnl-wbstairs-lobby": "place-hymnl", "70237": "place-clmnl", "node-jfk-crramp-cr": "place-jfk", "node-astao-revplatstair-platform": "place-astao", "North Station-02": "place-north", "node-398-rl": "place-sstat", "node-coecl-churchstair-platform": "place-coecl", "node-723-bl": "place-gover", "node-wlsta-stair4-lobby": "place-wlsta", "node-pktrm-stair8-rl": "place-pktrm", "node-spmnl-sfarepaid": "place-spmnl", "node-dwnxg-sumwashfare-paid": "place-dwnxg", "70021": "place-dwnxg", "node-haecl-congfarepaid": "place-haecl", "node-333-bottom": "place-brntn", "70006": "place-jaksn", "node-pktrm-sbwbstairs-gl": "place-pktrm", "node-821-lobby": "place-harsq", "node-armnl-eescstairs-escalator": "place-armnl", "node-cntsq-pearlstair-fareunpaid": "place-cntsq", "node-899-lobby": "place-nqncy", "node-bbsta-clar-farepaid": "place-bbsta", "Roslindale Village": "place-NB-0064", "door-brdwy-main": "place-brdwy", "64000": "place-dudly", "node-pktrm-tremwfare-unpaid": "place-pktrm", "door-bbsta-underpass": "place-bbsta", "node-asmnl-bealeramp": "place-asmnl", "node-wlsta-newpstairup-middle": "place-wlsta", "node-astao-folplatstair-platform": "place-astao", "32005": "place-qnctr", "node-pktrm-stair7-gl": "place-pktrm", "node-aqucl-sstatestairs-lobby": "place-aqucl", "node-wimnl-love-farepaid": "place-wimnl", "node-869-platform": "place-dwnxg", "door-andrw-dotave": "place-andrw", "node-wondl-ibplazaentrance": "place-wondl", "node-spmnl-obrienstairs-top": "place-spmnl", "70180": "place-bvmnl", "node-136-lobby": "place-rugg", "node-cntsq-essexstair-farepaid": "place-cntsq", "door-bvmnl-place": "place-bvmnl", "node-957-lobby": "place-fldcr", "node-945-platform": "place-mlmnl", "door-fldcr-busway": "place-fldcr", "West Natick": "place-WML-0199", "70138": "place-plsgr", "door-pktrm-winter": "place-pktrm", "node-sbmnl-132-lobby": "place-sbmnl", "door-portr-escal": "place-portr", "70162": "place-woodl", "North Station": "place-north", "70073": "place-chmnl", "door-newto-unionr": "place-newto", "node-887-platform": "place-bmmnl", "node-rugg-bus1stairs-busway": "place-rugg", "70134": "place-brico", "node-315-platform": "place-hymnl", "node-970-lobby": "place-asmnl", "node-981-street": "place-spmnl", "node-asmnl-mtpfarepaid": "place-asmnl", "70069": "place-cntsq", "Forest Hills": "place-forhl", "node-hymnl-massentrance": "place-hymnl", "node-qnctr-elevfarepaid": "place-qnctr", "node-854-lobby": "place-bbsta", "South Station-13": "place-sstat", "node-dwnxg-stair16-lobby": "place-dwnxg", "node-dwnxg-frnkfare-paid": "place-dwnxg", "node-harsq-harfarepaid": "place-harsq", "5327": "place-mlmnl", "node-907-passage": "place-haecl", "70144": "place-bucen", "node-astao-foldoorstair-ground": "place-astao", "Brandeis/ Roberts": "place-FR-0115", "70231": "place-tapst", "29014": "place-sull", "North Station-01": "place-north", "node-crtst-wtcexit-farepaid": "place-crtst", "node-921-platform": "place-prmnl", "node-335-lobby": "place-brntn", "74616": "place-crtst", "door-rbmnl-ocean": "place-rbmnl", "node-ccmnl-933-lobby": "place-ccmnl", "node-cntsq-obstair-fareunpaid": "place-cntsq", "Winchester Center": "place-NHRML-0078", "node-bmmnl-378stair-platform": "place-bmmnl", "node-430-landing": "place-kencl", "node-440-platform": "place-orhte", "Bellevue": "place-NB-0072", "node-gover-ebtransstairs-gl": "place-gover", "14748": "place-ER-0115", "node-andrw-nlobbycenter": "place-andrw", "door-cenav-ashmont": "place-cenav", "North Station-10": "place-north", "70023": "place-state", "node-jfk-ashganstair-platform": "place-jfk", "North Beverly": "place-ER-0208", "door-shmnl-savin": "place-shmnl", "node-pktrm-cpwbstairs-rl": "place-pktrm", "node-900-lobby": "place-nqncy", "node-701-bridge": "place-wondl", "node-dwnxg-stair2-rl": "place-dwnxg", "70243": "place-nuniv", "node-pktrm-sbwbstairs-rl": "place-pktrm", "node-411-lobby": "place-sstat", "node-wimnl-ibpaidstairs-platform": "place-wimnl", "node-harsq-upperramp-lobby": "place-harsq", "node-cntsq-obstair-platform": "place-cntsq", "node-438-lobby": "place-asmnl", "node-crtst-northentstair-lobby": "place-crtst", "node-mlmnl-commstair-lobby": "place-mlmnl", "node-jaksn-fareunpaid": "place-jaksn", "node-330-platform": "place-qnctr", "node-932-bridge": "place-aport", "node-chmnl-sbstairs-platform": "place-chmnl", "node-840-platform": "place-sull", "node-906-green": "place-haecl", "node-408-bridge": "place-aport", "node-142-platform": "place-bbsta", "node-800-lobby": "place-ogmnl", "70046": "place-mvbcl", "node-849-platform": "place-rugg", "node-haecl-congfhplatn-platform": "place-haecl", "node-jfk-bragasstair-lobby": "place-jfk", "node-jfk-busramp-lobby": "place-jfk", "node-ccmnl-933-platform": "place-ccmnl", "node-boyls-instair-platform": "place-boyls", "node-dwnxg-stair8-ol": "place-dwnxg", "node-851-bottom": "place-rugg", "node-sstat-399stair-lobby": "place-sstat", "node-welln-ogstair-platform": "place-welln", "70095": "place-jfk", "node-orhte-benn-fareunpaid": "place-orhte", "Anderson/ Woburn": "place-NHRML-0127", "70011": "place-rugg", "node-wlsta-park-fareunpaid": "place-wlsta", "node-aqucl-ebstatestairs-lobby": "place-aqucl", "node-850-platform": "place-rugg", "7096": "place-aport", "node-sstat-deweystair-lobby": "place-sstat", "node-830-lobby": "place-jfk", "Back Bay-01": "place-bbsta", "door-aport-buses": "place-aport", "node-446-gl": "place-gover", "node-knncl-nbmain-fareunpaid": "place-knncl", "70161": "place-river", "node-rcmnl-134-platform": "place-rcmnl", "node-pktrm-804unpaid": "place-pktrm", "Islington": "place-FB-0125", "door-cntsq-ibmass": "place-cntsq", "node-855-lobby": "place-bbsta", "door-cntsq-obmass": "place-cntsq", "70250": "place-brmnl", "node-armnl-nstairs-lobby": "place-armnl", "74630": "place-chels", "node-868-lobby": "place-brdwy", "node-515-lobby": "place-harsq", "74631": "place-chels", "node-887-lobby": "place-bmmnl", "door-newtn-station": "place-newtn", "door-knncl-nbmain": "place-knncl", "node-aqucl-ebstatestairs-platform": "place-aqucl", "node-sstat-399stair-middle": "place-sstat", "32001": "place-qnctr", "14150": "place-lech", "node-375-platform": "place-pktrm", "node-haecl-congogplats-platform": "place-haecl", "node-wtcst-farepaid": "place-wtcst", "node-pktrm-westfare-paid": "place-pktrm", "70255": "place-rvrwy", "node-148-platform": "place-tumnl", "70279": "place-astao", "door-masta-side": "place-masta", "node-pktrm-sbwinterstairs-lobby": "place-pktrm", "node-chncl-ogfareunpaid": "place-chncl", "node-bbsta-2clarexit-fareunpaid": "place-bbsta", "node-crtst-wtcexitstair-lobby": "place-crtst", "70079": "place-sstat", "node-400-rl": "place-sstat", "node-sstat-389stair-lobby": "place-sstat", "node-365-middle": "place-dwnxg", "node-gover-farepaid": "place-gover", "node-gover-ebtransstairs-bl": "place-gover", "70061": "place-alfcl", "70181": "place-bvmnl", "node-816-platform": "place-davis", "node-sstat-ashbrain-fareunpaid": "place-sstat", "38671": "place-brntn", "70169": "place-newtn", "node-shmnl-endstair-platform": "place-shmnl", "node-804-lobby": "place-pktrm", "node-bbsta-13stairs-lobby": "place-bbsta", "node-326-lobby": "place-nqncy", "node-cntsq-prospectstair-farepaid": "place-cntsq", "70201": "place-gover", "node-449-bridge": "place-wlsta", "node-aqucl-ebatlanticstairs-platform": "place-aqucl", "70246": "place-mfa", "node-889-unpaidbridge": "place-wimnl", "29005": "place-sull", "node-dwnxg-stair7-rl": "place-dwnxg", "Halifax": "place-PB-0281", "node-sbmnl-stairs-platform": "place-sbmnl", "node-davis-farepaid": "place-davis", "node-spmnl-ibstairs-lobby": "place-spmnl", "node-hymnl-newbury-fareunpaid": "place-hymnl", "Stoughton": "place-SB-0189", "node-fldcr-alewstair-platform": "place-fldcr", "91852": "place-NB-0120", "node-spmnl-obstairs-platform": "place-spmnl", "node-bbsta-upassestairs-top": "place-bbsta", "node-asmnl-peanbstair-platform": "place-asmnl", "node-923-platform": "place-aqucl", "node-387-lobby": "place-sstat", "node-ccmnl-stairs-lobby": "place-ccmnl", "node-aqucl-nstatestairs-landingtop": "place-aqucl", "node-380-platform": "place-wimnl", "node-rcmnl-134-lobby": "place-rcmnl", "node-aqucl-ebatlanticstairs-lobby": "place-aqucl", "70072": "place-knncl", "node-grnst-fareunpaid": "place-grnst", "node-383-lobby": "place-nqncy", "70179": "place-brkhl", "node-904-platform": "place-haecl", "70256": "place-rvrwy", "node-sbmnl-fareunpaid": "place-sbmnl", "node-pktrm-stair7-rl": "place-pktrm", "Worcester": "place-WML-0442", "node-sstat-400stair-rl": "place-sstat", "node-867-platform": "place-brdwy", "door-dwnxg-chauncy": "place-dwnxg", "node-tumnl-tre-fareunpaid": "place-tumnl", "node-shmnl-sh-farepaid": "place-shmnl", "node-956-bridge": "place-aport", "node-davis-colstairlow-lobby": "place-davis", "node-jfk-mainfarepaid": "place-jfk", "9328": "place-ogmnl", "door-sstat-atlantic": "place-sstat", "door-matt-square": "place-matt", "node-810-entrance": "place-qnctr", "door-bcnfd-bcnfield": "place-bcnfd", "node-bmmnl-379stair-platform": "place-bmmnl", "door-wondl-ocean": "place-wondl", "node-wlsta-stair5-bridge": "place-wlsta", "Mansfield": "place-NEC-2040", "Back Bay": "place-bbsta", "node-312-lobby": "place-mlmnl", "node-dwnxg-stair10-middle": "place-dwnxg", "70166": "place-eliot", "node-astao-foldoorstair-lobby": "place-astao", "70084": "place-andrw", "node-336-middle": "place-davis", "door-dwnxg-macys": "place-dwnxg", "node-wimnl-benn-farepaid": "place-wimnl", "door-armnl-garden": "place-armnl", "70089": "place-fldcr", "70269": "place-cenav", "node-823-platform": "place-pktrm", "node-702-bridge": "place-wondl", "39870": "place-MM-0186", "node-wtcst-ibstairs-platform": "place-wtcst", "node-grnst-844-platform": "place-grnst", "node-850-lobby": "place-rugg", "node-150-street": "place-prmnl", "node-nqncy-spstair-platform": "place-nqncy", "node-sbmnl-stairs-lobby": "place-sbmnl", "Montserrat": "place-GB-0198", "door-lech-exit": "place-lech", "node-dwnxg-stair4-platform": "place-dwnxg", "70080": "place-sstat", "node-smmnl-953-lobby": "place-smmnl", "70101": "place-qnctr", "node-333-top": "place-brntn", "node-orhte-ibunpaidstairs-bridge": "place-orhte", "node-bbsta-13stairs-platform": "place-bbsta", "node-harsq-bratstair-upper": "place-harsq", "node-dwnxg-stair11-lobby": "place-dwnxg", "node-forhl-slowbusstairs-busway": "place-forhl", "node-946-platform": "place-shmnl", "node-orhte-ibunpaidstairs-street": "place-orhte", "node-831-lobby": "place-jfk", "70236": "place-engav", "node-890-unpaidstreet": "place-wimnl", "node-516-lobby": "place-harsq", "70047": "place-aport", "node-713-street": "place-orhte", "node-andrw-sobstairs-lobby": "place-andrw", "node-378-lobby": "place-bmmnl", "door-harsq-square": "place-harsq", "node-hymnl-farepaid": "place-hymnl", "70207": "place-spmnl", "Andover": "place-WR-0228", "70276": "place-matt", "node-937-platform": "place-crtst", "North Station-09": "place-north", "node-103-lobby": "place-ogmnl", "node-379-platform": "place-bmmnl", "door-portr-elevators": "place-portr", "node-mlmnl-exitstair-lobby": "place-mlmnl", "node-wondl-footbridgeib": "place-wondl", "node-379-lobby": "place-bmmnl", "70019": "place-chncl", "node-907-platform": "place-haecl", "74615": "place-wtcst", "node-boyls-outstair-platform": "place-boyls", "node-735-bridge": "place-wlsta", "North Station-05": "place-north", "70200": "place-pktrm", "node-mlmnl-farepaid": "place-mlmnl", "node-bbsta-2clarexit-farepaid": "place-bbsta", "node-jaksn-stairs-platform": "place-jaksn", "Braintree-01": "place-brntn", "70137": "place-babck", "70145": "place-bucen", "node-sstat-finctrstair-lobby": "place-sstat", "5740": "place-mvbcl", "70078": "place-dwnxg", "node-prmnl-farepaid": "place-prmnl", "door-matt-neponset": "place-matt", "70064": "place-davis", "70049": "place-wimnl", "node-masta-unpramp-lobby": "place-masta", "node-309-platform": "place-welln", "node-968-lobby": "place-asmnl", "node-shmnl-platstair-platform": "place-shmnl", "door-state-meeting": "place-state", "node-crtst-wtcmain-farepaid": "place-crtst", "node-kencl-fvmramp-lobby": "place-kencl", "door-armnl-arlte": "place-armnl", "node-944-lobby": "place-mlmnl", "door-crtst-north": "place-crtst", "door-lech-entrance": "place-lech", "70020": "place-dwnxg", "door-mvbcl-lewis": "place-mvbcl", "node-jaksn-133-platform": "place-jaksn", "door-aqucl-atlanticelev": "place-aqucl", "door-rugg-ruggles": "place-rugg", "70218": "place-stpul", "node-pktrm-804paid": "place-pktrm", "node-pktrm-cpebstairs-rl": "place-pktrm", "20761": "place-harsq", "node-forhl-exitstairs-platform": "place-forhl", "node-965-entrance": "place-mvbcl", "door-chhil-bc": "place-chhil", "70113": "place-chill", "node-pktrm-wintfare-unpaid": "place-pktrm", "node-asmnl-peasbstair-lobby": "place-asmnl", "node-qnctr-elevfareunpaid": "place-qnctr", "node-nqncy-hstair-lobby": "place-nqncy", "node-coecl-ebfarepaid": "place-coecl", "node-853-platform": "place-bbsta", "node-423-platform": "place-shmnl", "node-jfk-sydneynstair-lobby": "place-jfk", "node-haecl-congfareunpaid": "place-haecl", "West Gloucester": "place-GB-0296", "71151": "place-kencl", "node-sstat-411stair-sl": "place-sstat", "70225": "place-bndhl", "node-sstat-alewife-fareunpaid": "place-sstat", "node-knncl-backsbstair-entrance": "place-knncl", "74613": "place-wtcst", "node-tumnl-trenbstairs-platform": "place-tumnl", "70053": "place-sdmnl", "node-927-sl": "place-sstat", "node-spmnl-nashuastairs-top": "place-spmnl", "node-bbsta-13clarexit-bottom": "place-bbsta", "node-980-lobby": "place-spmnl", "node-coecl-977-platform": "place-coecl", "node-andrw-slobbycenter": "place-andrw", "node-armnl-farepaid": "place-armnl", "node-362-entrance": "place-knncl", "node-938-lobby": "place-crtst", "node-spmnl-sfareunpaid": "place-spmnl", "70136": "place-babck", "node-dwnxg-stair2-ol": "place-dwnxg", "node-cntsq-obstair-farepaid": "place-cntsq", "node-jfk-ashgasstair-platform": "place-jfk", "70065": "place-portr", "70129": "place-grigg", "door-bbsta-garage": "place-bbsta", "node-436-lobby": "place-armnl", "node-ogmnl-washstair-street": "place-ogmnl", "70234": "place-denrd", "node-816-lobby": "place-davis", "node-410-platform": "place-aport", "door-symcl-ebchurch": "place-symcl", "node-143-lobby": "place-bbsta", "node-ogmnl-farepaid": "place-ogmnl", "North Scituate": "place-GRB-0233", "node-aport-ebpaidstairs-platform": "place-aport", "node-sstat-398stair-rl": "place-sstat", "node-bbsta-2stairs-platform": "place-bbsta", "door-asmnl-matpn": "place-asmnl", "door-sstat-dewey": "place-sstat", "node-coecl-eaststair-platform": "place-coecl", "door-rsmnl-wramp": "place-rsmnl", "door-orhte-saratoga": "place-orhte", "door-bcnfd-lot": "place-bcnfd", "door-pktrm-tremstair": "place-pktrm", "node-wlsta-lobbyramp-upper": "place-wlsta", "70028": "place-ccmnl", "node-kencl-commstair-lobby": "place-kencl", "node-sstat-919stair-sl": "place-sstat", "node-aport-buses-farepaid": "place-aport", "Canton Center": "place-SB-0156", "node-435-platform": "place-armnl", "door-smmnl-clemen": "place-smmnl", "node-davis-fareunpaid": "place-davis", "door-gover-main": "place-gover", "node-cntsq-westernstair-farepaid": "place-cntsq", "node-astao-folplatstair-lobby": "place-astao", "70103": "place-qamnl", "node-welln-ogstair-lobby": "place-welln", "70031": "place-sull", "node-408-platform": "place-aport", "node-harsq-nbramp-platform": "place-harsq", "70224": "place-sumav", "74634": "place-boxdt", "node-hymnl-wbstairs-platform": "place-hymnl", "node-sstat-398stair-sl": "place-sstat", "Lynn": "place-ER-0115", "node-wlsta-stair6gate-fareunpaid": "place-wlsta", "node-426-platform": "place-chmnl", "70241": "place-symcl", "70178": "place-brkhl", "node-sstat-382stair-rl": "place-sstat", "node-masta-unpstair-lobby": "place-masta", "node-866-platform": "place-knncl", "West Natick-S": "place-WML-0199", "node-ogmnl-washstair-lobby": "place-ogmnl", "15880": "place-orhte", "node-astao-717-platform": "place-astao", "node-708-lobby": "place-wondl", "node-105-lobby": "place-ogmnl", "node-symcl-wb-etop": "place-symcl", "node-811-lobby": "place-brntn", "node-harsq-harstair-lobby": "place-harsq", "door-alfcl-busway": "place-alfcl", "node-nqncy-senterstair-bus": "place-nqncy", "node-127-lobby": "place-forhl", "node-341-lobby": "place-davis", "node-998-rl": "place-dwnxg", "node-136-platform": "place-rugg", "node-904-lobby": "place-haecl", "door-aport-bremen": "place-aport", "node-harsq-sqlowstair-lobby": "place-harsq", "node-wondl-obplazastairs-street": "place-wondl", "Windsor Gardens": "place-FB-0166", "Route 128": "place-NEC-2173", "Wedgemere": "place-NHRML-0073", "TF Green Airport": "place-NEC-1768", "door-wlsta-beale": "place-wlsta", "node-971-lobby": "place-kencl", "door-tumnl-tremont": "place-tumnl", "node-aqucl-atlfareunpaid": "place-aqucl", "door-state-state": "place-state", "node-lbusstairs-upper": "place-sull", "70209": "place-lech", "node-921-lobby": "place-prmnl", "node-chmnl-nbstairs-platform": "place-chmnl", "node-dwnxg-wintwashfare-unpaid": "place-dwnxg", "Shirley": "place-FR-0394", "door-dwnxg-franklin": "place-dwnxg", "node-symcl-eb-midbottom": "place-symcl", "door-bbsta-dartmw": "place-bbsta", "node-pktrm-sbexitpaid": "place-pktrm", "Kingston": "place-KB-0351", "node-armnl-wbstairs-platform": "place-armnl", "node-crtst-wtcmain-fareunpaid": "place-crtst", "70124": "place-wrnst", "node-920-lobby": "place-prmnl", "node-brntn-nplatstairs-lobby": "place-brntn", "node-chncl-fhfareunpaid": "place-chncl", "node-astao-716-ground": "place-astao", "node-bbsta-upassestairs-bottom": "place-bbsta", "node-aqucl-statefarepaid": "place-aqucl", "70151": "place-kencl", "70068": "place-harsq", "70248": "place-lngmd", "70116": "place-sthld", "70219": "place-cool", "node-406-street": "place-aqucl", "node-nqncy-nstair-street": "place-nqncy", "node-bmmnl-fareunpaid": "place-bmmnl", "node-946-lobby": "place-shmnl", "node-308-platform": "place-sull", "node-forhl-splatstairs-platform": "place-forhl", "node-924-platform": "place-aqucl", "node-dwnxg-stair11-middle": "place-dwnxg", "node-jfk-bracolstair-platform": "place-jfk", "node-932-platform": "place-aport", "node-890-paidbridge": "place-wimnl", "node-pktrm-wbupassstairs-platform": "place-pktrm", "5271": "place-welln", "node-symcl-churstair-platform": "place-symcl", "node-coecl-ebfareunpaid": "place-coecl", "node-tumnl-trestairs-lobby": "place-tumnl", "node-149-lobby": "place-tumnl", "70235": "place-engav", "node-sstat-ashbrain-farepaid": "place-sstat", "node-wlsta-lobbyramp-lower": "place-wlsta", "7097": "place-aport", "node-mlmnl-olstairs-platform": "place-mlmnl", "Franklin": "place-FB-0275", "door-wondl-oceann": "place-wondl", "node-haecl-congfhstair-lobby": "place-haecl", "node-shmnl-sydstair-lobby": "place-shmnl", "node-389-rl": "place-sstat", "70253": "place-mispk", "node-armnl-ebstairs-lobby": "place-armnl", "door-harsq-brattle": "place-harsq", "node-343-lobby": "place-davis", "node-knncl-nbsec-fareunpaid": "place-knncl", "node-981-lobby": "place-spmnl", "door-knncl-sbsecond": "place-knncl", "node-aport-buswaystairs-lobby": "place-aport", "node-symcl-wb-wbottom": "place-symcl", "node-137-lobby": "place-rugg", "North Billerica": "place-NHRML-0218", "node-rugg-olexit-platform": "place-rugg", "node-gover-wbtransstairs-bl": "place-gover", "node-smmnl-sbstairs-platform": "place-smmnl", "Fairmount": "place-DB-2205", "node-143-platform": "place-bbsta", "South Attleboro": "place-NEC-1919", "node-haecl-congogplatn-platform": "place-haecl", "Wilmington": "place-NHRML-0152", "node-prmnl-prustair-lobby": "place-prmnl", "node-haecl-glstair-green": "place-haecl", "node-322-platform": "place-jfk", "node-dwnxg-sumwashfare-unpaid": "place-dwnxg", "node-397-street": "place-aqucl", "70176": "place-bcnfd", "70215": "place-kntst", "node-brntn-parking": "place-brntn", "node-spmnl-mfareunpaid": "place-spmnl", "70085": "place-jfk", "70205": "place-north", "node-307-platform": "place-sull", "Grafton": "place-WML-0364", "node-chncl-ogfarepaid": "place-chncl", "node-503-lobby": "place-prmnl", "node-brdwy-mainstairs-lobby": "place-brdwy", "node-926-lobby": "place-sstat", "node-426-lobby": "place-chmnl", "node-858-platform": "place-tumnl", "door-chncl-foresthills": "place-chncl", "door-bmmnl-main": "place-bmmnl", "node-prmnl-152stair-platform": "place-prmnl", "node-886-lobby": "place-bmmnl", "node-chncl-fhlower-landing": "place-chncl", "door-rugg-upper": "place-rugg", "node-bbsta-dartexit-platform": "place-bbsta", "node-999-rl": "place-dwnxg", "node-aqucl-statefareunpaid": "place-aqucl", "node-808-gl": "place-pktrm", "node-411-sl": "place-sstat", "node-nqncy-nhpstair-platform": "place-nqncy", "door-masta-main": "place-masta", "70171": "place-newto", "node-chncl-fhlower-lobby": "place-chncl", "Uphams Corner": "place-DB-2258", "Campello": "place-MM-0219", "door-asmnl-radford": "place-asmnl", "node-bmmnl-378stair-lobby": "place-bmmnl", "door-rbmnl-beach": "place-rbmnl", "node-138-top": "place-rugg", "node-sbmnl-845-platform": "place-sbmnl", "node-dwnxg-stair10-lobby": "place-dwnxg", "node-nqncy-nhfareunpaid": "place-nqncy", "node-405-street": "place-aqucl", "node-944-platform": "place-mlmnl", "node-tumnl-wash-fareunpaid": "place-tumnl", "door-capst-ashmont": "place-capst", "70040": "place-gover", "node-311-platform": "place-mlmnl", "node-952-platform": "place-chmnl", "node-andrw-sobstairs-platform": "place-andrw", "node-105-crplatform": "place-ogmnl", "Ipswich": "place-ER-0276", "Wickford Junction": "place-NEC-1659", "node-bbsta-olestairs-platform": "place-bbsta", "node-sstat-420stair-rl": "place-sstat", "node-969-platform": "place-asmnl", "node-tumnl-tre-farepaid": "place-tumnl", "node-jfk-ashsydstair-lobby": "place-jfk", "70272": "place-valrd", "node-wimnl-benn-fareunpaid": "place-wimnl", "node-413-landing": "place-crtst", "node-dwnxg-112fare-unpaid": "place-dwnxg", "node-445-platform": "place-gover", "node-smmnl-fareunpaid": "place-smmnl", "door-rsmnl-eramp": "place-rsmnl", "node-sull-nbstairs-platform": "place-sull", "Government Center-Brattle": "place-gover", "32004": "place-qnctr", "70208": "place-spmnl", "node-400-middle": "place-sstat", "node-chncl-fhupper-landing": "place-chncl", "door-rbmnl-main": "place-rbmnl", "node-cntsq-ibstair-fareunpaid": "place-cntsq", "node-980-platform": "place-spmnl", "node-801-platform": "place-ogmnl", "door-brkhl-bhs": "place-brkhl", "node-hymnl-newbury-farepaid": "place-hymnl", "node-qnctr-farepaid": "place-qnctr", "70107": "place-lake", "70071": "place-knncl", "node-bomnl-lobstair-lobby": "place-bomnl", "node-849-lobby": "place-rugg", "node-pktrm-stair8-gl": "place-pktrm", "node-104-street": "place-ogmnl", "node-sull-sbstairs-lobby": "place-sull", "node-forhl-splatstairs-lobby": "place-forhl", "node-434-lobby": "place-mvbcl", "door-dwnxg-101arch": "place-dwnxg", "node-lbusramp-upper": "place-sull", "node-masta-undernorth-lobby": "place-masta", "Needham Center": "place-NB-0127", "node-haecl-congogstairs-lobby": "place-haecl", "node-723-gl": "place-gover", "node-146-lobby": "place-tumnl", "node-asmnl-peasbstair-platform": "place-asmnl", "node-334-platform": "place-brntn", "node-872-lobby": "place-andrw", "node-343-entrance": "place-davis", "29003": "place-sull", "Westborough": "place-WML-0340", "node-394-lobby": "place-aqucl", "node-bbsta-olwstairs-platform": "place-bbsta", "node-jfk-sydfareunpaid": "place-jfk", "70163": "place-woodl", "node-342-entrance": "place-davis", "node-sstat-419stair-middle": "place-sstat", "node-939-lobby": "place-crtst", "node-bbsta-2clarexit-bottom": "place-bbsta", "node-dwnxg-112fare-paid": "place-dwnxg", "node-152-lobby": "place-prmnl", "door-astao-foley": "place-astao", "node-armnl-wbstairs-lobby": "place-armnl", "node-141-platform": "place-bbsta", "node-haecl-congfhplats-passage": "place-haecl", "node-davis-341stair-platform": "place-davis", "node-390-rl": "place-sstat", "node-wlsta-stair5-platform": "place-wlsta", "70070": "place-cntsq", "node-103-platform": "place-ogmnl", "node-chncl-oglower-landing": "place-chncl", "node-864-platform": "place-welln", "Norwood Depot": "place-FB-0143", "node-nqncy-sfareunpaid": "place-nqncy", "70206": "place-north", "70220": "place-cool", "door-asmnl-beale": "place-asmnl", "node-wondl-ibplazastairs-plaza": "place-wondl", "node-jfk-brasydstair-lobby": "place-jfk", "node-102-lobby": "place-ogmnl", "Talbot Avenue": "place-DB-2240", "node-sstat-400sl-middle": "place-sstat", "70043": "place-aqucl", "node-128-busway": "place-forhl", "door-rbmnl-shirley": "place-rbmnl", "node-smmnl-954-platform": "place-smmnl", "node-sstat-bldgstair-ground": "place-sstat", "70174": "place-rsmnl", "70120": "place-wascm", "node-shmnl-syd-fareunpaid": "place-shmnl", "node-jaksn-133-lobby": "place-jaksn", "node-jfk-bracolfareunpaid": "place-jfk", "70018": "place-chncl", "70056": "place-bmmnl", "node-tumnl-washsbstairs-platform": "place-tumnl", "node-858-lobby": "place-tumnl", "door-north-crcauseway": "place-north", "node-870-platform": "place-dwnxg", "node-jfk-oldstaire-lobby": "place-jfk", "node-bomnl-farepaid": "place-bomnl", "door-tumnl-washington": "place-tumnl", "70214": "place-hwsst", "door-sstat-reserve": "place-sstat", "70051": "place-orhte", "node-sstat-north-fareunpaid": "place-sstat", "node-astao-rev-farepaid": "place-astao", "node-sstat-north-farepaid": "place-sstat", "node-6476-lobby": "place-sstat", "door-ccmnl-main": "place-ccmnl", "node-312-platform": "place-mlmnl", "node-pktrm-sbexitunpaid": "place-pktrm", "70097": "place-nqncy", "node-342-lobby": "place-davis", "node-sbmnl-845-lobby": "place-sbmnl", "node-rugg-bus1stairs-lobby": "place-rugg", "node-astao-revdoorstair-ground": "place-astao", "node-pktrm-tremstairfare-paid": "place-pktrm", "node-848-busway": "place-rugg", "node-865-platform": "place-welln", "door-eliot-boylwr": "place-eliot", "node-ccmnl-farepaid": "place-ccmnl", "node-dwnxg-113fare-unpaid": "place-dwnxg", "node-978-lobby": "place-pktrm", "node-haecl-congfhstair-passage": "place-haecl", "node-qnctr-rdstair-platform": "place-qnctr", "70013": "place-masta", "door-forhl-south": "place-forhl", "70125": "place-wrnst", "node-437-platform": "place-asmnl", "Braintree": "place-brntn", "node-andrw-fareunpaid": "place-andrw", "70270": "place-cenav", "door-hymnl-newbury": "place-hymnl", "node-972-unpaidlobby": "place-kencl", "node-903-passage": "place-haecl", "70249": "place-brmnl", "node-wlsta-lobbysteps-lower": "place-wlsta", "node-wondl-ibfootbridgestairs-lobby": "place-wondl", "node-886-platform": "place-bmmnl", "70263": "place-cedgr", "node-wondl-farepaid": "place-wondl", "node-knncl-frontnbstair-platform": "place-knncl", "door-eliot-meredith": "place-eliot", "Bradford": "place-WR-0325", "node-chncl-oglower-lobby": "place-chncl", "Forest Hills-01": "place-forhl", "node-rugg-olnstairs-platform": "place-rugg", "node-890-unpaidbridge": "place-wimnl", "node-113-platform": "place-dwnxg", "door-woodl-main": "place-woodl", "node-haecl-passfhstair-platform": "place-haecl", "node-shmnl-syd-farepaid": "place-shmnl", "North Station-07": "place-north", "node-mvbcl-msqstair-lobby": "place-mvbcl", "node-ogmnl-banksstair-lobby": "place-ogmnl", "door-north-causeways": "place-north", "29007": "place-sull", "node-prmnl-920stair-platform": "place-prmnl", "29011": "place-sull", "door-bbsta-clarendon2": "place-bbsta", "node-sull-fareunpaid": "place-sull", "node-901-sl": "place-sstat", "door-sdmnl-benning": "place-sdmnl", "node-dwnxg-sumchyfare-unpaid": "place-dwnxg", "70227": "place-fbkst", "node-842-platform": "place-forhl", "door-harsq-church": "place-harsq", "29004": "place-sull", "node-320-lobby": "place-pktrm", "node-dwnxg-stair3-platform": "place-dwnxg", "node-aqucl-wbatlanticstairs-lobby": "place-aqucl", "70052": "place-orhte", "node-964-lobby": "place-armnl", "node-848-lobby": "place-rugg", "70012": "place-masta", "node-924-lobby": "place-aqucl", "node-919-sl": "place-sstat", "door-sstat-finctr": "place-sstat", "node-fldcr-alewstair-lobby": "place-fldcr", "Waltham": "place-FR-0098", "node-haecl-congfhplatn-passage": "place-haecl", "node-bbsta-upper-farepaid": "place-bbsta", "node-wlsta-newpramp-middle": "place-wlsta", "node-harsq-lowerstair-lower": "place-harsq", "node-crtst-ssexitstair-lobby": "place-crtst", "Wellesley Square": "place-WML-0147", "node-416-lobby": "place-crtst", "node-armnl-nwstairs-lobby": "place-armnl"}